auptitcafe/__init__.py
auptitcafe/emporter.py
auptitcafe/menus.py
auptitcafe/plat.py
auptitcafe-0.2.0.dist-info/METADATA
auptitcafe-0.2.0.dist-info/WHEEL
auptitcafe-0.2.0.dist-info/RECORD
