Metadata-Version: 2.4
Name: auptitcafe
Version: 0.2.0
Summary: SDK pour interagir avec http://auptitcafe.nc/menu/
Author: Adrien SALES
Author-email: Adrien.Sales@gmail.com
Requires-Python: >=3.9,<4.0
Classifier: Programming Language :: Python :: 3
Classifier: Programming Language :: Python :: 3.9
Classifier: Programming Language :: Python :: 3.10
Classifier: Programming Language :: Python :: 3.11
Classifier: Programming Language :: Python :: 3.12
Classifier: Programming Language :: Python :: 3.13
Classifier: Programming Language :: Python :: 3.14
Requires-Dist: beautifulsoup4 (>=4.12.2,<5.0.0)
